[
  {
    "_id": { "$oid": "66f300000000000000000001" },
    "title": "Frontend Developer",
    "description": "Build scalable UI components and dashboards using React.",
    "requirements": ["React", "JavaScript", "CSS", "REST API"],
    "salary": "12",
    "experienceLevel": 1,
    "location": "Bengaluru",
    "jobType": "Full-time",
    "position": 3,
    "company": { "$oid": "66f200000000000000000001" },
    "created_by": { "$oid": "66f100000000000000000001" },
    "applications": [],
    "createdAt": { "$date": "2026-03-03T09:00:00.000Z" },
    "updatedAt": { "$date": "2026-03-03T09:00:00.000Z" }
  },
  {
    "_id": { "$oid": "66f300000000000000000002" },
    "title": "Software Engineer, Backend",
    "description": "Design backend services and APIs for global products.",
    "requirements": ["Node.js", "Java", "Distributed Systems", "MongoDB"],
    "salary": "18",
    "experienceLevel": 2,
    "location": "Bengaluru",
    "jobType": "Full-time",
    "position": 2,
    "company": { "$oid": "66f200000000000000000001" },
    "created_by": { "$oid": "66f100000000000000000001" },
    "applications": [],
    "createdAt": { "$date": "2026-03-03T09:10:00.000Z" },
    "updatedAt": { "$date": "2026-03-03T09:10:00.000Z" }
  },
  {
    "_id": { "$oid": "66f300000000000000000003" },
    "title": "Cloud Engineer",
    "description": "Work on cloud infrastructure and deployment automation.",
    "requirements": ["Azure", "Terraform", "Docker", "CI/CD"],
    "salary": "16",
    "experienceLevel": 2,
    "location": "Hyderabad",
    "jobType": "Full-time",
    "position": 2,
    "company": { "$oid": "66f200000000000000000002" },
    "created_by": { "$oid": "66f100000000000000000001" },
    "applications": [],
    "createdAt": { "$date": "2026-03-03T09:20:00.000Z" },
    "updatedAt": { "$date": "2026-03-03T09:20:00.000Z" }
  },
  {
    "_id": { "$oid": "66f300000000000000000004" },
    "title": "Data Analyst",
    "description": "Analyze business datasets and build visual dashboards.",
    "requirements": ["SQL", "Python", "Power BI", "Statistics"],
    "salary": "10",
    "experienceLevel": 1,
    "location": "Hyderabad",
    "jobType": "Full-time",
    "position": 4,
    "company": { "$oid": "66f200000000000000000002" },
    "created_by": { "$oid": "66f100000000000000000001" },
    "applications": [],
    "createdAt": { "$date": "2026-03-03T09:30:00.000Z" },
    "updatedAt": { "$date": "2026-03-03T09:30:00.000Z" }
  },
  {
    "_id": { "$oid": "66f300000000000000000005" },
    "title": "SDE I",
    "description": "Build customer-facing and internal services at scale.",
    "requirements": ["Java", "Data Structures", "AWS", "API Design"],
    "salary": "14",
    "experienceLevel": 1,
    "location": "Bengaluru",
    "jobType": "Full-time",
    "position": 5,
    "company": { "$oid": "66f200000000000000000003" },
    "created_by": { "$oid": "66f100000000000000000002" },
    "applications": [],
    "createdAt": { "$date": "2026-03-03T09:40:00.000Z" },
    "updatedAt": { "$date": "2026-03-03T09:40:00.000Z" }
  },
  {
    "_id": { "$oid": "66f300000000000000000006" },
    "title": "DevOps Engineer",
    "description": "Improve release velocity through automation pipelines.",
    "requirements": ["Linux", "Docker", "Kubernetes", "Jenkins"],
    "salary": "15",
    "experienceLevel": 2,
    "location": "Bengaluru",
    "jobType": "Full-time",
    "position": 2,
    "company": { "$oid": "66f200000000000000000003" },
    "created_by": { "$oid": "66f100000000000000000002" },
    "applications": [],
    "createdAt": { "$date": "2026-03-03T09:50:00.000Z" },
    "updatedAt": { "$date": "2026-03-03T09:50:00.000Z" }
  },
  {
    "_id": { "$oid": "66f300000000000000000007" },
    "title": "UI Engineer",
    "description": "Design and implement polished web interfaces.",
    "requirements": ["React", "TypeScript", "Accessibility", "Figma"],
    "salary": "13",
    "experienceLevel": 1,
    "location": "Noida",
    "jobType": "Full-time",
    "position": 3,
    "company": { "$oid": "66f200000000000000000004" },
    "created_by": { "$oid": "66f100000000000000000002" },
    "applications": [],
    "createdAt": { "$date": "2026-03-03T10:00:00.000Z" },
    "updatedAt": { "$date": "2026-03-03T10:00:00.000Z" }
  },
  {
    "_id": { "$oid": "66f300000000000000000008" },
    "title": "Java Backend Developer",
    "description": "Develop backend microservices for document workflows.",
    "requirements": ["Java", "Spring Boot", "MySQL", "REST"],
    "salary": "17",
    "experienceLevel": 3,
    "location": "Noida",
    "jobType": "Full-time",
    "position": 2,
    "company": { "$oid": "66f200000000000000000004" },
    "created_by": { "$oid": "66f100000000000000000002" },
    "applications": [],
    "createdAt": { "$date": "2026-03-03T10:10:00.000Z" },
    "updatedAt": { "$date": "2026-03-03T10:10:00.000Z" }
  },
  {
    "_id": { "$oid": "66f300000000000000000009" },
    "title": "Data Engineer",
    "description": "Build robust data pipelines for recommendation systems.",
    "requirements": ["Python", "Spark", "Kafka", "Airflow"],
    "salary": "20",
    "experienceLevel": 3,
    "location": "Remote",
    "jobType": "Full-time",
    "position": 2,
    "company": { "$oid": "66f200000000000000000005" },
    "created_by": { "$oid": "66f100000000000000000003" },
    "applications": [],
    "createdAt": { "$date": "2026-03-03T10:20:00.000Z" },
    "updatedAt": { "$date": "2026-03-03T10:20:00.000Z" }
  },
  {
    "_id": { "$oid": "66f300000000000000000010" },
    "title": "Machine Learning Engineer",
    "description": "Train and deploy recommendation and ranking models.",
    "requirements": ["Python", "ML", "TensorFlow", "Feature Engineering"],
    "salary": "22",
    "experienceLevel": 3,
    "location": "Remote",
    "jobType": "Full-time",
    "position": 1,
    "company": { "$oid": "66f200000000000000000005" },
    "created_by": { "$oid": "66f100000000000000000003" },
    "applications": [],
    "createdAt": { "$date": "2026-03-03T10:30:00.000Z" },
    "updatedAt": { "$date": "2026-03-03T10:30:00.000Z" }
  },
  {
    "_id": { "$oid": "66f300000000000000000011" },
    "title": "Backend Engineer",
    "description": "Build APIs and services for mobility products.",
    "requirements": ["Node.js", "PostgreSQL", "Redis", "System Design"],
    "salary": "18",
    "experienceLevel": 2,
    "location": "Bengaluru",
    "jobType": "Full-time",
    "position": 2,
    "company": { "$oid": "66f200000000000000000006" },
    "created_by": { "$oid": "66f100000000000000000003" },
    "applications": [],
    "createdAt": { "$date": "2026-03-03T10:40:00.000Z" },
    "updatedAt": { "$date": "2026-03-03T10:40:00.000Z" }
  },
  {
    "_id": { "$oid": "66f300000000000000000012" },
    "title": "Android Developer",
    "description": "Develop rider and driver app features.",
    "requirements": ["Kotlin", "Android SDK", "REST", "Testing"],
    "salary": "14",
    "experienceLevel": 1,
    "location": "Bengaluru",
    "jobType": "Full-time",
    "position": 3,
    "company": { "$oid": "66f200000000000000000006" },
    "created_by": { "$oid": "66f100000000000000000003" },
    "applications": [],
    "createdAt": { "$date": "2026-03-03T10:50:00.000Z" },
    "updatedAt": { "$date": "2026-03-03T10:50:00.000Z" }
  },
  {
    "_id": { "$oid": "66f300000000000000000013" },
    "title": "Full Stack Developer",
    "description": "Build fintech dashboards and merchant tooling.",
    "requirements": ["React", "Node.js", "MongoDB", "Payments"],
    "salary": "11",
    "experienceLevel": 1,
    "location": "Noida",
    "jobType": "Full-time",
    "position": 4,
    "company": { "$oid": "66f200000000000000000007" },
    "created_by": { "$oid": "66f100000000000000000004" },
    "applications": [],
    "createdAt": { "$date": "2026-03-03T11:00:00.000Z" },
    "updatedAt": { "$date": "2026-03-03T11:00:00.000Z" }
  },
  {
    "_id": { "$oid": "66f300000000000000000014" },
    "title": "QA Engineer",
    "description": "Automate regression and API test coverage.",
    "requirements": ["Selenium", "Postman", "JavaScript", "CI"],
    "salary": "9",
    "experienceLevel": 1,
    "location": "Noida",
    "jobType": "Full-time",
    "position": 3,
    "company": { "$oid": "66f200000000000000000007" },
    "created_by": { "$oid": "66f100000000000000000004" },
    "applications": [],
    "createdAt": { "$date": "2026-03-03T11:10:00.000Z" },
    "updatedAt": { "$date": "2026-03-03T11:10:00.000Z" }
  },
  {
    "_id": { "$oid": "66f300000000000000000015" },
    "title": "Python Developer",
    "description": "Work on enterprise integration and automation services.",
    "requirements": ["Python", "FastAPI", "SQL", "Docker"],
    "salary": "10",
    "experienceLevel": 1,
    "location": "Pune",
    "jobType": "Full-time",
    "position": 4,
    "company": { "$oid": "66f200000000000000000008" },
    "created_by": { "$oid": "66f100000000000000000004" },
    "applications": [],
    "createdAt": { "$date": "2026-03-03T11:20:00.000Z" },
    "updatedAt": { "$date": "2026-03-03T11:20:00.000Z" }
  },
  {
    "_id": { "$oid": "66f300000000000000000016" },
    "title": "Data Scientist",
    "description": "Create predictive models for enterprise use cases.",
    "requirements": ["Python", "ML", "SQL", "Model Deployment"],
    "salary": "16",
    "experienceLevel": 2,
    "location": "Pune",
    "jobType": "Full-time",
    "position": 2,
    "company": { "$oid": "66f200000000000000000008" },
    "created_by": { "$oid": "66f100000000000000000004" },
    "applications": [],
    "createdAt": { "$date": "2026-03-03T11:30:00.000Z" },
    "updatedAt": { "$date": "2026-03-03T11:30:00.000Z" }
  }
]
